{"USP-S | Kill Confirmed (Well-Worn)": {"sugprice": 3087.1227499999995, "profit": 205, "limit": 2786, "timest": 1700344058}, "USP-S | Overgrowth (Field-Tested)": {"sugprice": 1804.9746666666665, "profit": 104, "limit": 1628, "timest": 1700344079}, "\u2605 Moto Gloves | Turtle (Battle-Scarred)": {"sugprice": 7909.951111111111, "profit": 530, "limit": 7138, "timest": 1700295275}, "\u2605 Navaja Knife | Scorched (Field-Tested)": {"sugprice": 6310.2986666666675, "profit": 394, "limit": 5695, "timest": 1700319900}, "\u2605 Driver Gloves | Racing Green (Battle-Scarred)": {"sugprice": 4036.09380952381, "profit": 210, "limit": 3642, "timest": 1700344291}, "StatTrak\u2122 M4A4 | Royal Paladin (Battle-Scarred)": {"sugprice": 2091.938, "profit": 264, "limit": 1887, "timest": 1700317383}, "StatTrak\u2122 M4A4 | The Emperor (Battle-Scarred)": {"sugprice": 2524, "profit": 178, "limit": 2277, "timest": 1700323069}, "StatTrak\u2122 USP-S | The Traitor (Well-Worn)": {"sugprice": 2120.3936, "profit": 226, "limit": 1913, "timest": 1700344013}, "USP-S | Printstream (Minimal Wear)": {"sugprice": 4435, "profit": 408, "limit": 4002, "timest": 1700264080}, "USP-S | Whiteout (Minimal Wear)": {"sugprice": 2644.8833333333337, "profit": 150, "limit": 2387, "timest": 1700344109}, "\u2605 Broken Fang Gloves | Needle Point (Battle-Scarred)": {"sugprice": 5200.413000000001, "profit": 424, "limit": 4693, "timest": 1700325814}, "\u2605 Broken Fang Gloves | Needle Point (Field-Tested)": {"sugprice": 5951.574500000001, "profit": 677, "limit": 5371, "timest": 1700344193}, "\u2605 Driver Gloves | Racing Green (Well-Worn)": {"sugprice": 4052.038571428571, "profit": 250, "limit": 3656, "timest": 1700344314}, "\u2605 Hand Wraps | Constrictor (Battle-Scarred)": {"sugprice": 4621.149, "profit": 260, "limit": 4170, "timest": 1700316893}, "\u2605 Hydra Gloves | Rattler (Field-Tested)": {"sugprice": 4125.1232432432425, "profit": 297, "limit": 3722, "timest": 1700344459}, "\u2605 Moto Gloves | Finish Line (Battle-Scarred)": {"sugprice": 6808.103, "profit": 387, "limit": 6144, "timest": 1700313892}, "\u2605 Navaja Knife | Forest DDPAT (Field-Tested)": {"sugprice": 6896.699230769231, "profit": 401, "limit": 6224, "timest": 1700344478}, "\u2605 Navaja Knife | Safari Mesh (Field-Tested)": {"sugprice": 7138.420243902438, "profit": 508, "limit": 6442, "timest": 1700344487}, "\u2605 Shadow Daggers | Bright Water (Field-Tested)": {"sugprice": 7223, "profit": 505, "limit": 6518, "timest": 1700322623}, "\u2605 Shadow Daggers | Rust Coat (Battle-Scarred)": {"sugprice": 6935.1609090909105, "profit": 430, "limit": 6258, "timest": 1700344511}, "\u2605 Broken Fang Gloves | Yellow-banded (Field-Tested)": {"sugprice": 6592.37875, "profit": 673, "limit": 5949, "timest": 1700344237}, "Vypa Sista of the Revolution | Guerrilla Warfare": {"sugprice": 1698.0029166666666, "profit": 176, "limit": 1532, "timest": 1700344110}, "StatTrak\u2122 M4A4 | \u9f8d\u738b (Dragon King) (Battle-Scarred)": {"sugprice": 1525.1675999999995, "profit": 180, "limit": 1376, "timest": 1700343902}, "\u2605 Hydra Gloves | Mangrove (Battle-Scarred)": {"sugprice": 4045.223823529411, "profit": 288, "limit": 3650, "timest": 1700344446}, "USP-S | Monster Mashup (Minimal Wear)": {"sugprice": 1912.8600000000001, "profit": 146, "limit": 1726, "timest": 1700344064}, "\u2605 Broken Fang Gloves | Yellow-banded (Battle-Scarred)": {"sugprice": 5745.07625, "profit": 502, "limit": 5184, "timest": 1700323458}, "\u2605 Hydra Gloves | Mangrove (Well-Worn)": {"sugprice": 4315.972941176471, "profit": 231, "limit": 3895, "timest": 1700344455}, "\u2605 Shadow Daggers | Scorched (Field-Tested)": {"sugprice": 7047.229166666665, "profit": 594, "limit": 6360, "timest": 1700344512}, "StatTrak\u2122 M4A4 | Desolate Space (Battle-Scarred)": {"sugprice": 1188, "profit": 105, "limit": 1072, "timest": 1700309654}, "StatTrak\u2122 P90 | Asiimov (Battle-Scarred)": {"sugprice": 1435.6964705882353, "profit": 127, "limit": 1295, "timest": 1700343954}, "\u2605 Hand Wraps | Desert Shamagh (Field-Tested)": {"sugprice": 4954.242187500001, "profit": 256, "limit": 4471, "timest": 1700336363}, "\u2605 Gut Knife | Forest DDPAT (Field-Tested)": {"sugprice": 7815.771176470587, "profit": 606, "limit": 7053, "timest": 1700344360}, "\u2605 Moto Gloves | Transport (Battle-Scarred)": {"sugprice": 5323.270588235295, "profit": 254, "limit": 4804, "timest": 1700343510}, "USP-S | The Traitor (Minimal Wear)": {"sugprice": 1443.8780000000002, "profit": 162, "limit": 1303, "timest": 1700344105}, "USP-S | Printstream (Well-Worn)": {"sugprice": 2708.8052000000002, "profit": 220, "limit": 2444, "timest": 1700344089}, "\u2605 Driver Gloves | Racing Green (Field-Tested)": {"sugprice": 4123.318780487804, "profit": 229, "limit": 3721, "timest": 1700344309}, "\u2605 Hand Wraps | Duct Tape (Field-Tested)": {"sugprice": 5294.105714285715, "profit": 370, "limit": 4777, "timest": 1700344434}, "USP-S | Monster Mashup (Well-Worn)": {"sugprice": 1314.3468750000004, "profit": 114, "limit": 1186, "timest": 1700344067}, "\u2605 Broken Fang Gloves | Unhinged (Battle-Scarred)": {"sugprice": 4980.250749999999, "profit": 430, "limit": 4494, "timest": 1700344206}, "\u2605 Hand Wraps | Arboreal (Field-Tested)": {"sugprice": 5741.35619047619, "profit": 416, "limit": 5181, "timest": 1700344416}, "USP-S | Kill Confirmed (Battle-Scarred)": {"sugprice": 3040.5209999999997, "profit": 200, "limit": 2744, "timest": 1700341232}, "USP-S | Serum (Field-Tested)": {"sugprice": 3403.589523809524, "profit": 298, "limit": 3071, "timest": 1700344096}, "\u2605 Hand Wraps | Giraffe (Battle-Scarred)": {"sugprice": 5855.3496428571425, "profit": 351, "limit": 5284, "timest": 1700344437}, "USP-S | Neo-Noir (Well-Worn)": {"sugprice": 1514.1169565217392, "profit": 104, "limit": 1366, "timest": 1700328304}, "\u2605 Survival Knife | Safari Mesh (Field-Tested)": {"sugprice": 7555.990588235295, "profit": 374, "limit": 6819, "timest": 1700344531}, "\u2605 Hydra Gloves | Case Hardened (Field-Tested)": {"sugprice": 8203.0425, "profit": 492, "limit": 7403, "timest": 1700344444}, "\u2605 Gut Knife | Rust Coat (Battle-Scarred)": {"sugprice": 7927.394761904761, "profit": 848, "limit": 7154, "timest": 1700344374}, "\u2605 Moto Gloves | Smoke Out (Battle-Scarred)": {"sugprice": 6775.608571428571, "profit": 461, "limit": 6114, "timest": 1700344468}, "\u2605 Hydra Gloves | Rattler (Battle-Scarred)": {"sugprice": 4428.553125, "profit": 472, "limit": 3996, "timest": 1700344457}, "StatTrak\u2122 M4A4 | Evil Daimyo (Minimal Wear)": {"sugprice": 742, "profit": 100, "limit": 669, "timest": 1700321907}, "StatTrak\u2122 SSG 08 | Dragonfire (Field-Tested)": {"sugprice": 3774.3855555555556, "profit": 358, "limit": 3406, "timest": 1700343970}, "\u2605 Specialist Gloves | Forest DDPAT (Battle-Scarred)": {"sugprice": 7965.405882352941, "profit": 524, "limit": 7188, "timest": 1700344522}, "StatTrak\u2122 M4A4 | Desert-Strike (Field-Tested)": {"sugprice": 1250.7204761904761, "profit": 100, "limit": 1128, "timest": 1700343825}, "\u2605 Broken Fang Gloves | Jade (Battle-Scarred)": {"sugprice": 7276, "profit": 781, "limit": 6566, "timest": 1700344187}, "StatTrak\u2122 M4A4 | Temukau (Battle-Scarred)": {"sugprice": 2528.9199999999996, "profit": 240, "limit": 2282, "timest": 1700343887}, "\u2605 Hydra Gloves | Rattler (Well-Worn)": {"sugprice": 4958.094285714285, "profit": 326, "limit": 4474, "timest": 1700344461}, "\u2605 Broken Fang Gloves | Needle Point (Well-Worn)": {"sugprice": 5424.298461538462, "profit": 307, "limit": 4895, "timest": 1700344197}, "StatTrak\u2122 USP-S | Neo-Noir (Field-Tested)": {"sugprice": 3067.939090909091, "profit": 355, "limit": 2768, "timest": 1700344005}, "USP-S | Whiteout (Battle-Scarred)": {"sugprice": 1673.4743478260868, "profit": 101, "limit": 1510, "timest": 1700342075}, "\u2605 Bloodhound Gloves | Guerrilla (Field-Tested)": {"sugprice": 5977.859285714287, "profit": 392, "limit": 5395, "timest": 1700344130}, "\u2605 Broken Fang Gloves | Unhinged (Well-Worn)": {"sugprice": 5112.469999999999, "profit": 276, "limit": 4614, "timest": 1700344214}, "\u2605 Gut Knife | Boreal Forest (Field-Tested)": {"sugprice": 7656.783076923078, "profit": 655, "limit": 6910, "timest": 1700344340}, "\u2605 Gut Knife | Bright Water (Field-Tested)": {"sugprice": 8217, "profit": 426, "limit": 7415, "timest": 1700338353}, "\u2605 Gut Knife | Safari Mesh (Field-Tested)": {"sugprice": 7057.182000000001, "profit": 396, "limit": 6369, "timest": 1700344395}, "\u2605 Hand Wraps | Arboreal (Well-Worn)": {"sugprice": 5829.65, "profit": 542, "limit": 5261, "timest": 1700344418}, "\u2605 Hand Wraps | Constrictor (Field-Tested)": {"sugprice": 5057.728611111111, "profit": 418, "limit": 4564, "timest": 1700344421}, "\u2605 Hand Wraps | Desert Shamagh (Well-Worn)": {"sugprice": 4495.349999999999, "profit": 258, "limit": 4057, "timest": 1700322520}, "\u2605 Navaja Knife | Damascus Steel (Field-Tested)": {"sugprice": 7095.971538461539, "profit": 431, "limit": 6404, "timest": 1700299341}, "\u2605 Navaja Knife | Night Stripe (Field-Tested)": {"sugprice": 6810.784374999999, "profit": 548, "limit": 6146, "timest": 1700344485}, "\u2605 Navaja Knife | Stained (Well-Worn)": {"sugprice": 7425, "profit": 642, "limit": 6701, "timest": 1700323555}, "\u2605 Navaja Knife | Tiger Tooth (Factory New)": {"sugprice": 12381.573571428571, "profit": 994, "limit": 11174, "timest": 1700344494}, "\u2605 Navaja Knife | Urban Masked (Field-Tested)": {"sugprice": 7010.866190476189, "profit": 620, "limit": 6327, "timest": 1700344497}, "\u2605 Shadow Daggers | Gamma Doppler (Factory New)": {"sugprice": 17843.93, "profit": 1301, "limit": 16104, "timest": 1700296748}, "\u2605 Shadow Daggers | Tiger Tooth (Factory New)": {"sugprice": 13344.345000000001, "profit": 893, "limit": 12043, "timest": 1700333130}, "\u2605 Sport Gloves | Bronze Morph (Field-Tested)": {"sugprice": 12247, "profit": 1248, "limit": 11052, "timest": 1700261936}, "\u2605 Survival Knife | Boreal Forest (Field-Tested)": {"sugprice": 7821.736111111111, "profit": 678, "limit": 7059, "timest": 1700344528}, "\u2605 Survival Knife | Forest DDPAT (Field-Tested)": {"sugprice": 8018.481818181817, "profit": 919, "limit": 7236, "timest": 1700344530}, "\u2605 Survival Knife | Scorched (Field-Tested)": {"sugprice": 7580.673000000001, "profit": 383, "limit": 6841, "timest": 1700344533}, "\u2605 Shadow Daggers | Black Laminate (Field-Tested)": {"sugprice": 7832.455555555554, "profit": 930, "limit": 7068, "timest": 1700344498}, "\u2605 Hand Wraps | Constrictor (Well-Worn)": {"sugprice": 4883.638125, "profit": 658, "limit": 4407, "timest": 1700344423}, "\u2605 Driver Gloves | Queen Jaguar (Field-Tested)": {"sugprice": 6066.674, "profit": 461, "limit": 5475, "timest": 1700344275}, "\u2605 Shadow Daggers | Ultraviolet (Well-Worn)": {"sugprice": 11075.0, "profit": 589, "limit": 9995, "timest": 1700341452}, "\u2605 Moto Gloves | 3rd Commando Company (Field-Tested)": {"sugprice": 6177.851500000001, "profit": 393, "limit": 5575, "timest": 1700344464}, "StatTrak\u2122 USP-S | Neo-Noir (Battle-Scarred)": {"sugprice": 2752.8904347826087, "profit": 143, "limit": 2484, "timest": 1700343116}, "UMP-45 | Blaze (Factory New)": {"sugprice": 1850.8265714285715, "profit": 178, "limit": 1670, "timest": 1700344030}, "\u2605 Falchion Knife | Tiger Tooth (Factory New)": {"sugprice": 22509.8375, "profit": 2061, "limit": 20315, "timest": 1700333925}, "\u2605 Hand Wraps | Duct Tape (Battle-Scarred)": {"sugprice": 4930.828333333334, "profit": 264, "limit": 4450, "timest": 1700332996}, "\u2605 Gut Knife | Doppler (Factory New)": {"sugprice": 16491.541, "profit": 817, "limit": 14883, "timest": 1700335066}, "\u2605 Huntsman Knife | Freehand (Field-Tested)": {"sugprice": 11207.92375, "profit": 621, "limit": 10115, "timest": 1700344440}, "StatTrak\u2122 Tec-9 | Decimator (Battle-Scarred)": {"sugprice": 1711, "profit": 196, "limit": 1544, "timest": 1700343976}, "StatTrak\u2122 M4A4 | Desolate Space (Well-Worn)": {"sugprice": 1241.694, "profit": 102, "limit": 1120, "timest": 1700343847}, "StatTrak\u2122 USP-S | The Traitor (Battle-Scarred)": {"sugprice": 2045.8895348837207, "profit": 204, "limit": 1846, "timest": 1700344012}, "\u2605 Driver Gloves | Convoy (Battle-Scarred)": {"sugprice": 6357.692, "profit": 458, "limit": 5737, "timest": 1700344249}, "StatTrak\u2122 MAC-10 | Neon Rider (Field-Tested)": {"sugprice": 1228.9464705882353, "profit": 101, "limit": 1109, "timest": 1700323776}, "StatTrak\u2122 M4A4 | The Battlestar (Field-Tested)": {"sugprice": 1332.9672727272728, "profit": 103, "limit": 1203, "timest": 1700337518}, "\u2605 Driver Gloves | Overtake (Field-Tested)": {"sugprice": 9058, "profit": 890, "limit": 8174, "timest": 1700344264}, "StatTrak\u2122 USP-S | Blueprint (Field-Tested)": {"sugprice": 944.4499999999999, "profit": 117, "limit": 852, "timest": 1700306479}, "\u2605 Driver Gloves | Overtake (Battle-Scarred)": {"sugprice": 6672.464761904763, "profit": 335, "limit": 6021, "timest": 1700344260}, "StatTrak\u2122 P250 | Muertos (Field-Tested)": {"sugprice": 1009.0241666666666, "profit": 110, "limit": 910, "timest": 1700343937}, "USP-S | Neo-Noir (Minimal Wear)": {"sugprice": 1568.279722222222, "profit": 100, "limit": 1415, "timest": 1700335948}, "USP-S | Kill Confirmed (Field-Tested)": {"sugprice": 3356, "profit": 188, "limit": 3028, "timest": 1700334753}, "\u2605 Driver Gloves | Queen Jaguar (Battle-Scarred)": {"sugprice": 5239.712093023255, "profit": 412, "limit": 4728, "timest": 1700344270}, "StatTrak\u2122 M4A4 | In Living Color (Field-Tested)": {"sugprice": 1127.99875, "profit": 135, "limit": 1018, "timest": 1700343877}, "\u2605 Specialist Gloves | Buckshot (Field-Tested)": {"sugprice": 5573.807272727273, "profit": 556, "limit": 5030, "timest": 1700344521}, "USP-S | Purple DDPAT (Field-Tested)": {"sugprice": 984.8916666666669, "profit": 101, "limit": 888, "timest": 1700343198}, "\u2605 Gut Knife | Ultraviolet (Field-Tested)": {"sugprice": 8095.9220000000005, "profit": 600, "limit": 7306, "timest": 1700344399}, "\u2605 Hand Wraps | Desert Shamagh (Battle-Scarred)": {"sugprice": 4719.142727272727, "profit": 692, "limit": 4259, "timest": 1700302770}, "StatTrak\u2122 SSG 08 | Turbo Peek (Battle-Scarred)": {"sugprice": 926.4964, "profit": 117, "limit": 836, "timest": 1700343972}, "\u2605 Shadow Daggers | Freehand (Field-Tested)": {"sugprice": 8350.61904761905, "profit": 414, "limit": 7536, "timest": 1700311109}, "USP-S | Monster Mashup (Battle-Scarred)": {"sugprice": 1276.2873333333332, "profit": 104, "limit": 1151, "timest": 1700338127}, "USP-S | Neo-Noir (Factory New)": {"sugprice": 2964.3805882352935, "profit": 283, "limit": 2675, "timest": 1700344068}, "StatTrak\u2122 USP-S | Printstream (Battle-Scarred)": {"sugprice": 4611.848518518517, "profit": 229, "limit": 4162, "timest": 1700334489}, "\u2605 Specialist Gloves | Buckshot (Battle-Scarred)": {"sugprice": 5128.856842105263, "profit": 487, "limit": 4628, "timest": 1700344519}, "USP-S | Orion (Minimal Wear)": {"sugprice": 4385.413846153846, "profit": 514, "limit": 3957, "timest": 1700322221}, "\u2605 Bowie Knife | Rust Coat (Battle-Scarred)": {"sugprice": 8266.279166666667, "profit": 522, "limit": 7460, "timest": 1700341295}, "USP-S | Caiman (Field-Tested)": {"sugprice": 3264.070606060606, "profit": 327, "limit": 2945, "timest": 1700334718}, "USP-S | Whiteout (Field-Tested)": {"sugprice": 1846.9179999999994, "profit": 138, "limit": 1666, "timest": 1700344108}, "\u2605 Hydra Gloves | Case Hardened (Battle-Scarred)": {"sugprice": 6843.388333333332, "profit": 434, "limit": 6176, "timest": 1700344442}, "USP-S | Monster Mashup (Field-Tested)": {"sugprice": 1312.2060869565219, "profit": 113, "limit": 1184, "timest": 1700344062}, "\u2605 Sport Gloves | Bronze Morph (Battle-Scarred)": {"sugprice": 10328.106315789473, "profit": 637, "limit": 9321, "timest": 1700344525}, "StatTrak\u2122 MP9 | Hydra (Battle-Scarred)": {"sugprice": 648.961724137931, "profit": 117, "limit": 585, "timest": 1700343919}, "\u2605 Bloodhound Gloves | Guerrilla (Battle-Scarred)": {"sugprice": 5688.352499999999, "profit": 343, "limit": 5133, "timest": 1700322293}, "StatTrak\u2122 M4A4 | Neo-Noir (Field-Tested)": {"sugprice": 1147.0994999999998, "profit": 117, "limit": 1035, "timest": 1700335399}, "StatTrak\u2122 USP-S | Stainless (Battle-Scarred)": {"sugprice": 957.5274074074077, "profit": 120, "limit": 864, "timest": 1700312396}, "StatTrak\u2122 USP-S | Blueprint (Battle-Scarred)": {"sugprice": 914, "profit": 102, "limit": 824, "timest": 1700322090}, "USP-S | Kill Confirmed (Minimal Wear)": {"sugprice": 5608.522727272728, "profit": 338, "limit": 5061, "timest": 1700344056}, "\u2605 Broken Fang Gloves | Unhinged (Field-Tested)": {"sugprice": 5256.44551724138, "profit": 298, "limit": 4743, "timest": 1700344211}, "StatTrak\u2122 USP-S | Ticket to Hell (Factory New)": {"sugprice": 735.7827272727271, "profit": 131, "limit": 664, "timest": 1700317615}, "StatTrak\u2122 M4A4 | Cyber Security (Well-Worn)": {"sugprice": 1545.6715384615384, "profit": 111, "limit": 1394, "timest": 1700330212}, "\u2605 Navaja Knife | Marble Fade (Factory New)": {"sugprice": 15299.755000000001, "profit": 1529, "limit": 13808, "timest": 1700344480}, "StatTrak\u2122 M4A1-S | Player Two (Battle-Scarred)": {"sugprice": 3169.4473076923077, "profit": 307, "limit": 2860, "timest": 1700343813}, "StatTrak\u2122 USP-S | Cyrex (Factory New)": {"sugprice": 1092.7875000000001, "profit": 103, "limit": 986, "timest": 1700282300}, "StatTrak\u2122 P250 | Asiimov (Field-Tested)": {"sugprice": 826.6214285714286, "profit": 156, "limit": 746, "timest": 1700316413}, "StatTrak\u2122 Tec-9 | Blue Titanium (Factory New)": {"sugprice": 725.4150000000001, "profit": 110, "limit": 654, "timest": 1700322077}, "USP-S | Orion (Field-Tested)": {"sugprice": 4220.41894736842, "profit": 203, "limit": 3808, "timest": 1700324905}, "USP-S | The Traitor (Field-Tested)": {"sugprice": 887.1976190476189, "profit": 132, "limit": 800, "timest": 1700323424}, "StatTrak\u2122 M4A4 | Cyber Security (Battle-Scarred)": {"sugprice": 1589.0180952380954, "profit": 196, "limit": 1434, "timest": 1700343817}, "StatTrak\u2122 M4A4 | Tooth Fairy (Well-Worn)": {"sugprice": 569.4518749999999, "profit": 110, "limit": 513, "timest": 1700306265}, "StatTrak\u2122 P250 | Asiimov (Well-Worn)": {"sugprice": 803.4281249999999, "profit": 119, "limit": 725, "timest": 1700343935}, "StatTrak\u2122 Tec-9 | Fuel Injector (Well-Worn)": {"sugprice": 402.49764705882353, "profit": 100, "limit": 363, "timest": 1700276701}, "StatTrak\u2122 P90 | Trigon (Field-Tested)": {"sugprice": 1236.7, "profit": 108, "limit": 1116, "timest": 1700343961}, "USP-S | Royal Blue (Field-Tested)": {"sugprice": 852.4315789473685, "profit": 106, "limit": 769, "timest": 1700306711}, "Operation Bravo Case": {"sugprice": 3183.349574468085, "profit": 180, "limit": 2872, "timest": 1700275037}, "P2000 | Fire Elemental (Well-Worn)": {"sugprice": 1330.428, "profit": 160, "limit": 1200, "timest": 1700275096}, "P90 | Asiimov (Minimal Wear)": {"sugprice": 1328.1976470588236, "profit": 128, "limit": 1198, "timest": 1700275238}, "P90 | Death by Kitty (Field-Tested)": {"sugprice": 3249.787666666666, "profit": 370, "limit": 2932, "timest": 1700275246}, "Sir Bloody Miami Darryl | The Professionals": {"sugprice": 4118.192499999999, "profit": 231, "limit": 3716, "timest": 1700275389}, "SSG 08 | Blood in the Water (Minimal Wear)": {"sugprice": 3266.3210810810806, "profit": 169, "limit": 2947, "timest": 1700275428}, "SSG 08 | Dragonfire (Minimal Wear)": {"sugprice": 1065.6491666666668, "profit": 111, "limit": 961, "timest": 1700275459}, "StatTrak\u2122 AK-47 | Aquamarine Revenge (Battle-Scarred)": {"sugprice": 3963.840833333333, "profit": 291, "limit": 3577, "timest": 1700275473}, "StatTrak\u2122 AK-47 | Head Shot (Well-Worn)": {"sugprice": 3411.3662499999996, "profit": 657, "limit": 3078, "timest": 1700275489}, "StatTrak\u2122 AK-47 | Ice Coaled (Minimal Wear)": {"sugprice": 2240.873076923077, "profit": 178, "limit": 2022, "timest": 1700275504}, "StatTrak\u2122 AK-47 | Ice Coaled (Well-Worn)": {"sugprice": 1559.0438888888891, "profit": 160, "limit": 1407, "timest": 1700275515}, "StatTrak\u2122 AK-47 | Neon Revolution (Battle-Scarred)": {"sugprice": 3201.2640625000004, "profit": 261, "limit": 2889, "timest": 1700275533}, "StatTrak\u2122 AK-47 | Neon Revolution (Field-Tested)": {"sugprice": 3160.734782608696, "profit": 152, "limit": 2852, "timest": 1700275535}, "StatTrak\u2122 AK-47 | Neon Rider (Battle-Scarred)": {"sugprice": 4533.846818181818, "profit": 505, "limit": 4091, "timest": 1700275540}, "StatTrak\u2122 AK-47 | Nightwish (Field-Tested)": {"sugprice": 2430.3234782608693, "profit": 168, "limit": 2193, "timest": 1700275548}, "StatTrak\u2122 AK-47 | Phantom Disruptor (Minimal Wear)": {"sugprice": 1434, "profit": 145, "limit": 1294, "timest": 1700275571}, "StatTrak\u2122 AK-47 | Redline (Battle-Scarred)": {"sugprice": 2099.540833333333, "profit": 145, "limit": 1894, "timest": 1700275581}, "StatTrak\u2122 AK-47 | Redline (Field-Tested)": {"sugprice": 3244.9871428571428, "profit": 305, "limit": 2928, "timest": 1700275584}, "StatTrak\u2122 AK-47 | The Empress (Battle-Scarred)": {"sugprice": 5133.427727272727, "profit": 255, "limit": 4632, "timest": 1700275603}, "StatTrak\u2122 AWP | Chromatic Aberration (Field-Tested)": {"sugprice": 1606.8659090909093, "profit": 172, "limit": 1450, "timest": 1700275679}, "StatTrak\u2122 AWP | Chromatic Aberration (Minimal Wear)": {"sugprice": 2914.521333333333, "profit": 204, "limit": 2630, "timest": 1700275694}, "StatTrak\u2122 AWP | Corticera (Field-Tested)": {"sugprice": 2826.4306250000004, "profit": 292, "limit": 2550, "timest": 1700275697}, "StatTrak\u2122 AWP | Elite Build (Battle-Scarred)": {"sugprice": 2401.4269696969695, "profit": 447, "limit": 2167, "timest": 1700275732}, "StatTrak\u2122 AWP | Elite Build (Well-Worn)": {"sugprice": 2461.434166666667, "profit": 376, "limit": 2221, "timest": 1700275736}, "StatTrak\u2122 AWP | Fever Dream (Field-Tested)": {"sugprice": 1329.6656, "profit": 145, "limit": 1200, "timest": 1700275769}, "StatTrak\u2122 AWP | Hyper Beast (Battle-Scarred)": {"sugprice": 3866.163684210527, "profit": 282, "limit": 3489, "timest": 1700275775}, "StatTrak\u2122 AWP | Neo-Noir (Field-Tested)": {"sugprice": 3965.5083333333337, "profit": 366, "limit": 3578, "timest": 1700275804}, "StatTrak\u2122 Desert Eagle | Code Red (Battle-Scarred)": {"sugprice": 3161.7619047619046, "profit": 326, "limit": 2853, "timest": 1700275864}, "StatTrak\u2122 Desert Eagle | Code Red (Well-Worn)": {"sugprice": 3176.226, "profit": 335, "limit": 2866, "timest": 1700275874}, "StatTrak\u2122 Desert Eagle | Conspiracy (Field-Tested)": {"sugprice": 1211.2609523809524, "profit": 102, "limit": 1093, "timest": 1700275883}, "StatTrak\u2122 Desert Eagle | Kumicho Dragon (Battle-Scarred)": {"sugprice": 2702.7519047619044, "profit": 129, "limit": 2439, "timest": 1700275914}, "StatTrak\u2122 Desert Eagle | Mecha Industries (Well-Worn)": {"sugprice": 990, "profit": 112, "limit": 893, "timest": 1700275954}, "StatTrak\u2122 Desert Eagle | Ocean Drive (Battle-Scarred)": {"sugprice": 2950.2642105263158, "profit": 270, "limit": 2662, "timest": 1700275988}, "StatTrak\u2122 Desert Eagle | Printstream (Battle-Scarred)": {"sugprice": 4495.390571428572, "profit": 227, "limit": 4057, "timest": 1700275999}, "StatTrak\u2122 Desert Eagle | Printstream (Field-Tested)": {"sugprice": 4847.852000000001, "profit": 451, "limit": 4375, "timest": 1700276010}, "StatTrak\u2122 Glock-18 | Neo-Noir (Battle-Scarred)": {"sugprice": 1840.1380000000004, "profit": 195, "limit": 1660, "timest": 1700276094}, "StatTrak\u2122 M4A1-S | Chantico's Fire (Battle-Scarred)": {"sugprice": 3288.491034482758, "profit": 338, "limit": 2967, "timest": 1700276285}, "StatTrak\u2122 M4A1-S | Chantico's Fire (Well-Worn)": {"sugprice": 3473.82, "profit": 212, "limit": 3135, "timest": 1700276290}, "StatTrak\u2122 M4A1-S | Decimator (Battle-Scarred)": {"sugprice": 2229.5249999999996, "profit": 213, "limit": 2012, "timest": 1700276294}, "StatTrak\u2122 M4A1-S | Decimator (Field-Tested)": {"sugprice": 2225.8400000000006, "profit": 131, "limit": 2008, "timest": 1700276297}, "StatTrak\u2122 M4A1-S | Hyper Beast (Battle-Scarred)": {"sugprice": 3266.632222222222, "profit": 305, "limit": 2948, "timest": 1700276324}, "StatTrak\u2122 M4A1-S | Leaded Glass (Battle-Scarred)": {"sugprice": 1030.454285714286, "profit": 121, "limit": 929, "timest": 1700276328}, "StatTrak\u2122 M4A1-S | Mecha Industries (Field-Tested)": {"sugprice": 5076.5740000000005, "profit": 372, "limit": 4581, "timest": 1700276332}, "StatTrak\u2122 M4A1-S | Nightmare (Well-Worn)": {"sugprice": 1683, "profit": 173, "limit": 1518, "timest": 1700276338}, "StatTrak\u2122 SSG 08 | Turbo Peek (Field-Tested)": {"sugprice": 913.4594736842105, "profit": 103, "limit": 824, "timest": 1700343973}, "USP-S | Serum (Minimal Wear)": {"sugprice": 3588.865, "profit": 256, "limit": 3238, "timest": 1700311806}, "USP-S | Stainless (Minimal Wear)": {"sugprice": 616, "profit": 128, "limit": 555, "timest": 1700305866}, "StatTrak\u2122 P90 | Shapewood (Field-Tested)": {"sugprice": 395, "profit": 113, "limit": 356, "timest": 1700327063}, "Tec-9 | Decimator (Field-Tested)": {"sugprice": 880.9865116279071, "profit": 100, "limit": 795, "timest": 1700333501}, "Trapper | Guerrilla Warfare": {"sugprice": 834.2253846153848, "profit": 123, "limit": 752, "timest": 1700322155}, "USP-S | Para Green (Battle-Scarred)": {"sugprice": 570.3433333333332, "profit": 119, "limit": 514, "timest": 1700327447}, "StatTrak\u2122 M4A4 | Temukau (Field-Tested)": {"sugprice": 3266.8242857142855, "profit": 323, "limit": 2948, "timest": 1700303890}, "USP-S | Para Green (Field-Tested)": {"sugprice": 608, "profit": 128, "limit": 548, "timest": 1700322227}, "StatTrak\u2122 P250 | Visions (Field-Tested)": {"sugprice": 416.59000000000003, "profit": 102, "limit": 375, "timest": 1700329735}, "StatTrak\u2122 Sawed-Off | Kiss\u2665Love (Battle-Scarred)": {"sugprice": 378.1913333333332, "profit": 100, "limit": 341, "timest": 1700312318}, "StatTrak\u2122 MP7 | Abyssal Apparition (Minimal Wear)": {"sugprice": 508.424375, "profit": 102, "limit": 458, "timest": 1700336861}, "StatTrak\u2122 Tec-9 | Fuel Injector (Battle-Scarred)": {"sugprice": 394.14170212765947, "profit": 114, "limit": 355, "timest": 1700309874}, "StatTrak\u2122 MP9 | Starlight Protector (Field-Tested)": {"sugprice": 717.6951851851852, "profit": 109, "limit": 647, "timest": 1700321981}, "StatTrak\u2122 P2000 | Imperial Dragon (Field-Tested)": {"sugprice": 650.5592592592593, "profit": 136, "limit": 587, "timest": 1700326946}, "StatTrak\u2122 M4A4 | Spider Lily (Battle-Scarred)": {"sugprice": 387.8028571428572, "profit": 112, "limit": 349, "timest": 1700315410}, "StatTrak\u2122 M4A4 | Spider Lily (Well-Worn)": {"sugprice": 384.7342105263158, "profit": 110, "limit": 347, "timest": 1700309716}, "StatTrak\u2122 P250 | Visions (Well-Worn)": {"sugprice": 416.82944444444445, "profit": 138, "limit": 376, "timest": 1700312299}, "StatTrak\u2122 UMP-45 | Momentum (Field-Tested)": {"sugprice": 520.4213333333333, "profit": 125, "limit": 469, "timest": 1700330704}, "StatTrak\u2122 MP7 | Bloodsport (Well-Worn)": {"sugprice": 593.097142857143, "profit": 113, "limit": 535, "timest": 1700343917}}